MANIFEST.in
README.txt
setup.cfg
setup.py
trytond/__init__.py
trytond/modules/__init__.py
trytond/modules/contract/__init__.py
trytond/modules/contract/__tryton__.py
trytond/modules/contract/configuration.py
trytond/modules/contract/configuration.xml
trytond/modules/contract/contract.py
trytond/modules/contract/contract.xml
trytond/modules/contract/invoice.py
trytond/modules/contract/invoice.xml
trytond/modules/contract/party.py
trytond/modules/contract/party.xml
trytond/modules/contract/tests/__init__.py
trytond_contract.egg-info/PKG-INFO
trytond_contract.egg-info/SOURCES.txt
trytond_contract.egg-info/dependency_links.txt
trytond_contract.egg-info/entry_points.txt
trytond_contract.egg-info/namespace_packages.txt
trytond_contract.egg-info/not-zip-safe
trytond_contract.egg-info/requires.txt
trytond_contract.egg-info/top_level.txt