Metadata-Version: 1.0
Name: trytond-contract
Version: 2.2.2
Summary: Generate recurrent invoices based on agreements.
